Workbook

Sheet Overview
B2: SaaS Market 2026 — Pricing & Positioning Analysis
B3: Source: ComparEdge (Kaggle) — 331 SaaS products across 28 categories, snapshot dated 2026-04-27
B5: Total Products | C5: Categories | D5: Median Entry Price | E5: % With Free Tier
B6: =COUNTA(Products!B2:B332) | C6: =COUNTA('Category Summary'!A2:A29) | D6: =TEXT(MEDIAN(Products!S2:S332),"$0.00/mo") | E6: =ROUND(COUNTIF(Products!J2:J332,TRUE)/COUNTA(Products!B2:B332)*100,1)&"%"
B9: How to read this workbook
B10: • Products — one row per SaaS product (cleaned from a SQLite relational export). 'entry_price_comparable' is a helper column used by every downstream formula.
B11: • Pricing Plans — one row per pricing tier per product (1,013 total).
B12: • Category Summary — category-level stats computed live with AVERAGEIF/COUNTIFS formulas against the Products sheet, not pasted-in numbers.
B13: • Billing Models — mix of flat / per-seat / usage-based / per-project billing across all pricing plans.
B14: • Dashboard — charts built from the Category Summary and Billing Models tables.
B17: Known data quality issues (see sql/02_data_quality_checks.sql for detection queries)
B18: • 'ai-tools' was a phantom umbrella category (104 products claimed, 0 actually tagged) — removed; the real AI products live in the ai-* subcategories + LLM.
B19: • 'DEX' pricing_plans.price_monthly stores swap-fee percentages, not USD/month subscription prices — excluded from all price comparisons (price_comparable = FALSE).
B20: • products.review_count is 0 for every row (unpopulated in the source data) — not used anywhere as a reliability signal.
B21: • ~11 products have no overall_rating and ~89 have at least one custom/'Contact Sales' plan — both kept as-is (blank/N/A) rather than guessed at.
B22: • A few category names were auto-titlecased acronyms ('Crm', 'Dex', 'Vpn') — corrected to CRM, DEX, VPN, DeFi Tools.

Sheet Dashboard
B2: SaaS Market 2026 — Dashboard

Sheet Products
A1: product_id | B1: name | C1: category_slug | D1: category_name | E1: overall_rating | F1: g2_rating | G1: capterra_rating | H1: founded_year | I1: hq_location | J1: has_free_tier | K1: has_free_trial | L1: has_custom_pricing | M1: price_comparable | N1: entry_price | O1: max_price_monthly | P1: plan_count | Q1: feature_count | R1: website_url | S1: entry_price_comparable
A2: 67 | B2: 10Web | C2: website-builders | D2: Website Builders | E2: 4.55 | F2: 4.6 | G2: 4.5 | H2: 2017 | I2: Yerevan, Armenia / Wilmington, DE | J2: FALSE | K2: FALSE | L2: FALSE | M2: TRUE | N2: 10 | O2: 60 | P2: 3 | Q2: 9 | R2: https://10web.io | S2: =IF(M2,N2,"")
A3: 157 | B3: 1Password | C3: password-managers | D3: Password Managers | E3: 4.75 | F3: 4.8 | G3: 4.7 | H3: 2006 | J3: FALSE | K3: FALSE | L3: FALSE | M3: TRUE | N3: 2.99 | O3: 7.99 | P3: 3 | Q3: 14 | R3: https://1password.com | S3: =IF(M3,N3,"")
A4: 292 | B4: 1inch | C4: defi-tools | D4: DeFi Tools | E4: 4.3 | F4: 4.3 | H4: 2019 | I4: Cayman Islands | J4: TRUE | K4: FALSE | L4: FALSE | M4: TRUE | O4: 0 | P4: 1 | Q4: 10 | R4: https://1inch.io | S4: =IF(M4,N4,"")
A5: 265 | B5: 3Commas | C5: crypto-trading-bots | D5: Crypto Trading Bots | E5: 4.25 | F5: 4.3 | G5: 4.2 | H5: 2017 | I5: Tallinn, Estonia | J5: TRUE | K5: FALSE | L5: FALSE | M5: TRUE | N5: 15 | O5: 60 | P5: 4 | Q5: 12 | R5: https://3commas.io | S5: =IF(M5,N5,"")
A6: 87 | B6: A2 Hosting | C6: cloud-hosting | D6: Cloud Hosting | E6: 4.35 | F6: 4.3 | G6: 4.4 | H6: 2003 | I6: Ann Arbor, MI | J6: FALSE | K6: FALSE | L6: FALSE | M6: TRUE | N6: 2.99 | O6: 14.99 | P6: 4 | Q6: 9 | R6: https://www.a2hosting.com | S6: =IF(M6,N6,"")
A7: 196 | B7: AI21 Studio | C7: ai-writing | D7: AI Writing | E7: 4.35 | F7: 4.4 | G7: 4.3 | H7: 2017 | J7: TRUE | K7: FALSE | L7: TRUE | M7: TRUE | N7: 39 | O7: 39 | P7: 3 | Q7: 6 | R7: https://studio.ai21.com | S7: =IF(M7,N7,"")
A8: 43 | B8: AWeber | C8: email-marketing | D8: Email Marketing | E8: 4.3 | F8: 4.2 | G8: 4.4 | H8: 1998 | I8: Chalfont, PA | J8: TRUE | K8: FALSE | L8: FALSE | M8: TRUE | N8: 14.99 | O8: 899 | P8: 4 | Q8: 12 | R8: https://www.aweber.com | S8: =IF(M8,N8,"")
A9: 286 | B9: Accointing (Blockpit) | C9: crypto-tax | D9: Crypto Tax | E9: 4.1 | F9: 4.1 | H9: 2017 | I9: Vienna, Austria | J9: TRUE | K9: FALSE | L9: FALSE | M9: TRUE | N9: 49 | O9: 199 | P9: 4 | Q9: 6 | R9: https://www.blockpit.io | S9: =IF(M9,N9,"")
A10: 39 | B10: ActiveCampaign | C10: email-marketing | D10: Email Marketing | E10: 4.55 | F10: 4.5 | G10: 4.6 | H10: 2003 | I10: Chicago, IL | J10: FALSE | K10: FALSE | L10: FALSE | M10: TRUE | N10: 15 | O10: 145 | P10: 4 | Q10: 17 | R10: https://www.activecampaign.com | S10: =IF(M10,N10,"")
A11: 170 | B11: Adobe Firefly | C11: ai-image | D11: AI Image Generators | E11: 4.45 | F11: 4.4 | G11: 4.5 | H11: 2023 | J11: TRUE | K11: FALSE | L11: FALSE | M11: TRUE | N11: 5 | O11: 5 | P11: 2 | Q11: 5 | R11: https://firefly.adobe.com | S11: =IF(M11,N11,"")
A12: 98 | B12: Adobe Illustrator | C12: design-tools | D12: Design Tools | E12: 4.65 | F12: 4.6 | G12: 4.7 | H12: 1987 | I12: San Jose, CA (Adobe) | J12: FALSE | K12: FALSE | L12: FALSE | M12: TRUE | N12: 22.99 | O12: 59.99 | P12: 2 | Q12: 6 | R12: https://www.adobe.com/products/illustrator.html | S12: =IF(M12,N12,"")
A13: 99 | B13: Adobe Photoshop | C13: design-tools | D13: Design Tools | E13: 4.7 | F13: 4.6 | G13: 4.8 | H13: 1990 | I13: San Jose, CA (Adobe) | J13: FALSE | K13: FALSE | L13: FALSE | M13: TRUE | N13: 9.99 | O13: 59.99 | P13: 3 | Q13: 8 | R13: https://www.adobe.com/products/photoshop.html | S13: =IF(M13,N13,"")
A14: 222 | B14: Adobe Podcast (Enhance) | C14: ai-voice | D14: AI Voice & Audio | E14: 4.6 | F14: 4.6 | G14: 4.6 | H14: 2022 | J14: TRUE | K14: FALSE | L14: FALSE | M14: TRUE | N14: 5 | O14: 5 | P14: 2 | Q14: 4 | R14: https://podcast.adobe.com | S14: =IF(M14,N14,"")
A15: 93 | B15: Adobe XD | C15: design-tools | D15: Design Tools | E15: 4.4 | F15: 4.3 | G15: 4.5 | H15: 2016 | I15: San Jose, CA (Adobe) | J15: FALSE | K15: FALSE | L15: FALSE | M15: TRUE | N15: 59.99 | O15: 59.99 | P15: 1 | Q15: 14 | R15: https://www.adobe.com/products/xd.html | S15: =IF(M15,N15,"")
A16: 97 | B16: Affinity Designer | C16: design-tools | D16: Design Tools | E16: 4.6 | F16: 4.5 | G16: 4.7 | H16: 2014 | I16: Nottingham, UK (Canva) | J16: FALSE | K16: FALSE | L16: FALSE | M16: TRUE | N16: 14.99 | O16: 169.99 | P16: 3 | Q16: 6 | R16: https://affinity.serif.com/en-us/designer/ | S16: =IF(M16,N16,"")
A17: 14 | B17: Airtable | C17: project-management | D17: Project Management | E17: 4.65 | F17: 4.6 | G17: 4.7 | H17: 2012 | I17: San Francisco, CA | J17: TRUE | K17: FALSE | L17: TRUE | M17: TRUE | N17: 20 | O17: 45 | P17: 4 | Q17: 13 | R17: https://airtable.com | S17: =IF(M17,N17,"")
A18: 118 | B18: Akaunting | C18: accounting | D18: Accounting | E18: 4.3 | F18: 4.2 | G18: 4.4 | H18: 2017 | I18: London, UK | J18: TRUE | K18: FALSE | L18: FALSE | M18: TRUE | N18: 15 | O18: 15 | P18: 2 | Q18: 13 | R18: https://akaunting.com | S18: =IF(M18,N18,"")
A19: 272 | B19: Altrady | C19: crypto-trading-bots | D19: Crypto Trading Bots | E19: 4.2 | F19: 4.2 | H19: 2018 | I19: Amsterdam, Netherlands | J19: TRUE | K19: FALSE | L19: FALSE | M19: TRUE | N19: 19 | O19: 55 | P19: 4 | Q19: 9 | R19: https://altrady.com | S19: =IF(M19,N19,"")
A20: 71 | B20: Amazon Web Services (AWS) | C20: cloud-hosting | D20: Cloud Hosting | E20: 4.55 | F20: 4.5 | G20: 4.6 | H20: 2006 | I20: Seattle, WA | J20: TRUE | K20: FALSE | L20: TRUE | M20: TRUE | O20: 0 | P20: 2 | Q20: 19 | R20: https://aws.amazon.com | S20: =IF(M20,N20,"")
A21: 212 | B21: Anthropic API (Claude) | C21: llm | D21: Large Language Models | E21: 4.65 | F21: 4.7 | G21: 4.6 | H21: 2021 | J21: FALSE | K21: FALSE | L21: TRUE | M21: TRUE | O21: 0 | P21: 2 | Q21: 9 | R21: https://anthropic.com/api | S21: =IF(M21,N21,"")
A22: 129 | B22: Around | C22: video-conferencing | D22: Video Conferencing | E22: 4.35 | F22: 4.4 | G22: 4.3 | H22: 2020 | I22: San Francisco, CA (Miro) | J22: TRUE | K22: FALSE | L22: FALSE | M22: TRUE | O22: 0 | P22: 1 | Q22: 4 | R22: https://www.around.co | S22: =IF(M22,N22,"")
A23: 3 | B23: Asana | C23: project-management | D23: Project Management | E23: 4.45 | F23: 4.4 | G23: 4.5 | H23: 2008 | I23: San Francisco, CA | J23: TRUE | K23: FALSE | L23: TRUE | M23: TRUE | N23: 10.99 | O23: 24.99 | P23: 4 | Q23: 15 | R23: https://asana.com | S23: =IF(M23,N23,"")
A24: 36 | B24: Attio | C24: crm | D24: CRM | E24: 4.75 | F24: 4.8 | G24: 4.7 | H24: 2019 | I24: London, UK | J24: TRUE | K24: FALSE | L24: TRUE | M24: TRUE | N24: 34 | O24: 69 | P24: 4 | Q24: 11 | R24: https://attio.com | S24: =IF(M24,N24,"")
A25: 250 | B25: AutoGPT | C25: ai-agents | D25: AI Agents | E25: 3.75 | F25: 3.8 | G25: 3.7 | H25: 2023 | J25: TRUE | K25: FALSE | L25: FALSE | M25: TRUE | O25: 0 | P25: 2 | Q25: 18 | R25: https://agpt.co | S25: =IF(M25,N25,"")
A26: 307 | B26: BONKbot | C26: crypto-telegram-bots | D26: Crypto Telegram Bots | E26: 4 | F26: 4 | H26: 2023 | I26: Unknown | J26: TRUE | K26: FALSE | L26: FALSE | M26: TRUE | O26: 0 | P26: 1 | Q26: 4 | R26: https://bonkbot.io | S26: =IF(M26,N26,"")
A27: 306 | B27: Banana Gun | C27: crypto-telegram-bots | D27: Crypto Telegram Bots | E27: 4.3 | F27: 4.3 | H27: 2023 | I27: Unknown | J27: TRUE | K27: FALSE | L27: FALSE | M27: TRUE | O27: 0 | P27: 1 | Q27: 9 | R27: https://bananagun.io | S27: =IF(M27,N27,"")
A28: 7 | B28: Basecamp | C28: project-management | D28: Project Management | E28: 4.2 | F28: 4.1 | G28: 4.3 | H28: 2004 | I28: Chicago, IL | J28: TRUE | K28: FALSE | L28: FALSE | M28: TRUE | N28: 15 | O28: 299 | P28: 3 | Q28: 9 | R28: https://basecamp.com | S28: =IF(M28,N28,"")
A29: 226 | B29: Beautiful.ai | C29: ai-productivity | D29: AI Productivity | E29: 4.45 | F29: 4.4 | G29: 4.5 | H29: 2016 | J29: FALSE | K29: FALSE | L29: TRUE | M29: TRUE | N29: 12 | O29: 40 | P29: 3 | Q29: 10 | R29: https://beautiful.ai | S29: =IF(M29,N29,"")
A30: 114 | B30: Bench | C30: accounting | D30: Accounting | E30: 4.45 | F30: 4.5 | G30: 4.4 | H30: 2012 | I30: Vancouver, Canada | J30: FALSE | K30: FALSE | L30: FALSE | M30: TRUE | N30: 189 | O30: 339 | P30: 2 | Q30: 7 | R30: https://bench.co | S30: =IF(M30,N30,"")
A31: 297 | B31: Binance | C31: crypto-exchanges | D31: Crypto Exchanges | E31: 4.35 | F31: 4.4 | G31: 4.3 | H31: 2017 | I31: Cayman Islands | J31: TRUE | K31: FALSE | L31: TRUE | M31: TRUE | O31: 0 | P31: 3 | Q31: 11 | R31: https://www.binance.com | S31: =IF(M31,N31,"")
A32: 304 | B32: Bitget | C32: crypto-exchanges | D32: Crypto Exchanges | E32: 4.1 | F32: 4.1 | H32: 2018 | I32: Seychelles | J32: TRUE | K32: FALSE | L32: TRUE | M32: TRUE | O32: 0 | P32: 3 | Q32: 7 | R32: https://www.bitget.com | S32: =IF(M32,N32,"")
A33: 268 | B33: Bitsgap | C33: crypto-trading-bots | D33: Crypto Trading Bots | E33: 4.2 | F33: 4.2 | H33: 2018 | I33: Tallinn, Estonia | J33: TRUE | K33: FALSE | L33: FALSE | M33: TRUE | N33: 23 | O33: 119 | P33: 4 | Q33: 8 | R33: https://bitsgap.com | S33: =IF(M33,N33,"")
A34: 158 | B34: Bitwarden | C34: password-managers | D34: Password Managers | E34: 4.75 | F34: 4.7 | G34: 4.8 | H34: 2016 | J34: TRUE | K34: FALSE | L34: FALSE | M34: TRUE | N34: 1 | O34: 4 | P34: 3 | Q34: 9 | R34: https://bitwarden.com | S34: =IF(M34,N34,"")
A35: 311 | B35: Bloom | C35: crypto-telegram-bots | D35: Crypto Telegram Bots | E35: 4.2 | F35: 4.2 | H35: 2023 | I35: Unknown | J35: TRUE | K35: FALSE | L35: FALSE | M35: TRUE | O35: 0 | P35: 1 | Q35: 14 | R35: https://bloombot.app | S35: =IF(M35,N35,"")
A36: 88 | B36: Bluehost | C36: cloud-hosting | D36: Cloud Hosting | E36: 4 | F36: 3.7 | G36: 4.3 | H36: 2003 | I36: Burlington, MA (Newfold Digital) | J36: FALSE | K36: FALSE | L36: FALSE | M36: TRUE | N36: 2.95 | O36: 9.95 | P36: 4 | Q36: 16 | R36: https://www.bluehost.com | S36: =IF(M36,N36,"")
A37: 206 | B37: Bolt.new | C37: ai-coding | D37: AI Coding | E37: 4.55 | F37: 4.6 | G37: 4.5 | H37: 2024 | J37: TRUE | K37: FALSE | L37: FALSE | M37: TRUE | N37: 25 | O37: 30 | P37: 3 | Q37: 8 | R37: https://bolt.new | S37: =IF(M37,N37,"")
A38: 116 | B38: Bonsai | C38: accounting | D38: Accounting | E38: 4.4 | F38: 4.3 | G38: 4.5 | H38: 2016 | I38: San Francisco, CA | J38: FALSE | K38: FALSE | L38: FALSE | M38: TRUE | N38: 9 | O38: 29 | P38: 3 | Q38: 10 | R38: https://www.hellobonsai.com | S38: =IF(M38,N38,"")
A39: 258 | B39: Botpress | C39: ai-assistants | D39: AI Assistants | E39: 4.55 | F39: 4.6 | G39: 4.5 | H39: 2016 | J39: TRUE | K39: FALSE | L39: FALSE | M39: TRUE | N39: 89 | O39: 89 | P39: 2 | Q39: 13 | R39: https://botpress.com | S39: =IF(M39,N39,"")
A40: 40 | B40: Brevo (Sendinblue) | C40: email-marketing | D40: Email Marketing | E40: 4.5 | F40: 4.5 | G40: 4.5 | H40: 2012 | I40: Paris, France | J40: FALSE | K40: FALSE | L40: TRUE | M40: TRUE | N40: 9 | O40: 49 | P40: 4 | Q40: 17 | R40: https://www.brevo.com | S40: =IF(M40,N40,"")
A41: 310 | B41: BullX | C41: crypto-telegram-bots | D41: Crypto Telegram Bots | E41: 4.1 | F41: 4.1 | H41: 2024 | I41: Unknown | J41: TRUE | K41: FALSE | L41: FALSE | M41: TRUE | O41: 0 | P41: 1 | Q41: 9 | R41: https://bullx.io | S41: =IF(M41,N41,"")
A42: 136 | B42: Butter | C42: video-conferencing | D42: Video Conferencing | E42: 4.65 | F42: 4.7 | G42: 4.6 | H42: 2021 | I42: Berlin, Germany | J42: TRUE | K42: FALSE | L42: TRUE | M42: TRUE | N42: 25 | O42: 25 | P42: 3 | Q42: 8 | R42: https://butter.us | S42: =IF(M42,N42,"")
A43: 53 | B43: Buttondown | C43: email-marketing | D43: Email Marketing | E43: 4.7 | F43: 4.6 | G43: 4.8 | H43: 2017 | I43: Seattle, WA | J43: TRUE | K43: FALSE | L43: FALSE | M43: TRUE | N43: 9 | O43: 79 | P43: 4 | Q43: 6 | R43: https://buttondown.com | S43: =IF(M43,N43,"")
A44: 300 | B44: Bybit | C44: crypto-exchanges | D44: Crypto Exchanges | E44: 4.2 | F44: 4.2 | H44: 2018 | I44: Dubai, UAE | J44: TRUE | K44: FALSE | L44: TRUE | M44: TRUE | O44: 0 | P44: 3 | Q44: 7 | R44: https://www.bybit.com | S44: =IF(M44,N44,"")
A45: 135 | B45: Cal.com (Cal Video) | C45: video-conferencing | D45: Video Conferencing | E45: 4.65 | F45: 4.7 | G45: 4.6 | H45: 2021 | I45: San Francisco, CA | J45: TRUE | K45: FALSE | L45: TRUE | M45: TRUE | N45: 12 | O45: 12 | P45: 3 | Q45: 9 | R45: https://cal.com | S45: =IF(M45,N45,"")
A46: 50 | B46: Campaign Monitor | C46: email-marketing | D46: Email Marketing | E46: 4.3 | F46: 4.1 | G46: 4.5 | H46: 2004 | I46: Nashville, TN (Marigold) | J46: FALSE | K46: FALSE | L46: FALSE | M46: TRUE | N46: 12 | O46: 159 | P46: 3 | Q46: 15 | R46: https://www.campaignmonitor.com | S46: =IF(M46,N46,"")
A47: 92 | B47: Canva | C47: design-tools | D47: Design Tools | E47: 4.7 | F47: 4.7 | G47: 4.7 | H47: 2012 | I47: Sydney, Australia | J47: TRUE | K47: FALSE | L47: TRUE | M47: TRUE | N47: 10 | O47: 15 | P47: 4 | Q47: 12 | R47: https://www.canva.com | S47: =IF(M47,N47,"")
A48: 197 | B48: Canva AI | C48: ai-image | D48: AI Image Generators | E48: 4.7 | F48: 4.7 | G48: 4.7 | H48: 2013 | J48: TRUE | K48: FALSE | L48: FALSE | M48: TRUE | N48: 10 | O48: 15 | P48: 3 | Q48: 11 | R48: https://canva.com/ai-image-generator | S48: =IF(M48,N48,"")
A49: 230 | B49: CapCut AI | C49: ai-video | D49: AI Video | E49: 4.65 | F49: 4.6 | G49: 4.7 | H49: 2020 | J49: TRUE | K49: FALSE | L49: FALSE | M49: TRUE | N49: 10 | O49: 20 | P49: 3 | Q49: 6 | R49: https://capcut.com | S49: =IF(M49,N49,"")
A50: 35 | B50: Capsule CRM | C50: crm | D50: CRM | E50: 4.6 | F50: 4.7 | G50: 4.5 | H50: 2009 | I50: Manchester, UK | J50: TRUE | K50: FALSE | L50: FALSE | M50: TRUE | N50: 21 | O50: 75 | P50: 5 | Q50: 12 | R50: https://capsulecrm.com | S50: =IF(M50,N50,"")
A51: 60 | B51: Carrd | C51: website-builders | D51: Website Builders | E51: 4.55 | F51: 4.5 | G51: 4.6 | H51: 2016 | I51: Remote | J51: TRUE | K51: FALSE | L51: FALSE | M51: TRUE | N51: 9 | O51: 49 | P51: 4 | Q51: 8 | R51: https://carrd.co | S51: =IF(M51,N51,"")
A52: 211 | B52: Character.AI | C52: ai-assistants | D52: AI Assistants | E52: 4.25 | F52: 4.3 | G52: 4.2 | H52: 2021 | J52: TRUE | K52: FALSE | L52: FALSE | M52: TRUE | N52: 10 | O52: 10 | P52: 2 | Q52: 5 | R52: https://character.ai | S52: =IF(M52,N52,"")
A53: 151 | B53: ChatGPT | C53: llm | D53: Large Language Models | E53: 4.65 | F53: 4.7 | G53: 4.6 | H53: 2022 | J53: TRUE | K53: FALSE | L53: FALSE | M53: TRUE | N53: 20 | O53: 30 | P53: 3 | Q53: 7 | R53: https://chatgpt.com | S53: =IF(M53,N53,"")
A54: 257 | B54: Chatbase | C54: ai-assistants | D54: AI Assistants | E54: 4.35 | F54: 4.4 | G54: 4.3 | H54: 2023 | J54: TRUE | K54: FALSE | L54: FALSE | M54: TRUE | N54: 32 | O54: 300 | P54: 4 | Q54: 7 | R54: https://chatbase.co | S54: =IF(M54,N54,"")
A55: 152 | B55: Claude | C55: llm | D55: Large Language Models | E55: 4.55 | F55: 4.6 | G55: 4.5 | H55: 2023 | J55: TRUE | K55: FALSE | L55: FALSE | M55: TRUE | N55: 20 | O55: 20 | P55: 2 | Q55: 10 | R55: https://claude.ai | S55: =IF(M55,N55,"")
A56: 241 | B56: Claude 3.5 Sonnet | C56: llm | D56: Large Language Models | E56: 4.6 | F56: 4.7 | G56: 4.5 | H56: 2024 | J56: TRUE | K56: FALSE | L56: FALSE | M56: TRUE | N56: 20 | O56: 30 | P56: 3 | Q56: 16 | R56: https://claude.ai | S56: =IF(M56,N56,"")
A57: 145 | B57: ClickFunnels | C57: website-builders | D57: Website Builders | E57: 4.25 | F57: 4 | G57: 4.5 | H57: 2014 | I57: Eagle, ID | J57: FALSE | K57: FALSE | L57: FALSE | M57: TRUE | N57: 81 | O57: 248 | P57: 2 | Q57: 13 | R57: https://www.clickfunnels.com | S57: =IF(M57,N57,"")
A58: 2 | B58: ClickUp | C58: project-management | D58: Project Management | E58: 4.65 | F58: 4.7 | G58: 4.6 | H58: 2017 | I58: San Diego, CA | J58: TRUE | K58: FALSE | L58: TRUE | M58: TRUE | N58: 7 | O58: 12 | P58: 4 | Q58: 17 | R58: https://clickup.com | S58: =IF(M58,N58,"")
A59: 26 | B59: Close | C59: crm | D59: CRM | E59: 4.7 | F59: 4.7 | G59: 4.7 | H59: 2013 | I59: San Francisco, CA | J59: FALSE | K59: FALSE | L59: FALSE | M59: TRUE | N59: 49 | O59: 139 | P59: 3 | Q59: 10 | R59: https://close.com | S59: =IF(M59,N59,"")
A60: 72 | B60: Cloudways | C60: cloud-hosting | D60: Cloud Hosting | E60: 4.6 | F60: 4.5 | G60: 4.7 | H60: 2011 | I60: Dubai, UAE (DigitalOcean) | J60: FALSE | K60: FALSE | L60: FALSE | M60: TRUE | N60: 14 | O60: 54 | P60: 4 | Q60: 20 | R60: https://www.cloudways.com | S60: =IF(M60,N60,"")
A61: 17 | B61: Coda | C61: project-management | D61: Project Management | E61: 4.65 | F61: 4.7 | G61: 4.6 | H61: 2014 | I61: Mountain View, CA | J61: TRUE | K61: FALSE | L61: TRUE | M61: TRUE | N61: 10 | O61: 30 | P61: 4 | Q61: 14 | R61: https://coda.io | S61: =IF(M61,N61,"")
A62: 178 | B62: Codeium | C62: ai-coding | D62: AI Coding | E62: 4.55 | F62: 4.6 | G62: 4.5 | H62: 2022 | J62: TRUE | K62: FALSE | L62: TRUE | M62: TRUE | N62: 20 | O62: 40 | P62: 4 | Q62: 5 | R62: https://windsurf.com | S62: =IF(M62,N62,"")
A63: 215 | B63: Cohere | C63: llm | D63: Large Language Models | E63: 4.45 | F63: 4.5 | G63: 4.4 | H63: 2019 | J63: TRUE | K63: FALSE | L63: TRUE | M63: TRUE | O63: 0 | P63: 3 | Q63: 8 | R63: https://cohere.com | S63: =IF(M63,N63,"")
A64: 291 | B64: CoinGecko | C64: crypto-portfolio-trackers | D64: Crypto Portfolio Trackers | E64: 4.7 | F64: 4.7 | H64: 2014 | I64: Kuala Lumpur, Malaysia | J64: TRUE | K64: FALSE | L64: FALSE | M64: TRUE | N64: 7.49 | O64: 7.49 | P64: 2 | Q64: 5 | R64: https://www.coingecko.com | S64: =IF(M64,N64,"")
A65: 273 | B65: CoinGlass | C65: crypto-analytics | D65: Crypto Analytics | E65: 4.4 | F65: 4.4 | H65: 2020 | I65: Unknown | J65: TRUE | K65: FALSE | L65: FALSE | M65: TRUE | N65: 29 | O65: 79 | P65: 3 | Q65: 2 | R65: https://www.coinglass.com | S65: =IF(M65,N65,"")
A66: 285 | B66: CoinLedger | C66: crypto-tax | D66: Crypto Tax | E66: 4.25 | F66: 4.2 | G66: 4.3 | H66: 2018 | I66: Indianapolis, USA | J66: TRUE | K66: FALSE | L66: FALSE | M66: TRUE | N66: 49 | O66: 199 | P66: 4 | Q66: 4 | R66: https://coinledger.io | S66: =IF(M66,N66,"")
A67: 287 | B67: CoinStats | C67: crypto-portfolio-trackers | D67: Crypto Portfolio Trackers | E67: 4.4 | F67: 4.4 | H67: 2017 | I67: Yerevan, Armenia | J67: TRUE | K67: FALSE | L67: FALSE | M67: TRUE | N67: 13.99 | O67: 13.99 | P67: 2 | Q67: 12 | R67: https://coinstats.app | S67: =IF(M67,N67,"")
A68: 282 | B68: CoinTracker | C68: crypto-tax | D68: Crypto Tax | E68: 4.15 | F68: 4.1 | G68: 4.2 | H68: 2017 | I68: San Francisco, USA | J68: TRUE | K68: FALSE | L68: FALSE | M68: TRUE | N68: 59 | O68: 599 | P68: 4 | Q68: 7 | R68: https://www.cointracker.io | S68: =IF(M68,N68,"")
A69: 298 | B69: Coinbase | C69: crypto-exchanges | D69: Crypto Exchanges | E69: 4.05 | F69: 4.1 | G69: 4 | H69: 2012 | I69: San Francisco, USA | J69: TRUE | K69: FALSE | L69: FALSE | M69: TRUE | N69: 29.99 | O69: 29.99 | P69: 3 | Q69: 10 | R69: https://www.coinbase.com | S69: =IF(M69,N69,"")
A70: 320 | B70: Coinbase Wallet | C70: crypto-wallets | D70: Crypto Wallets | E70: 4.1 | F70: 4.1 | H70: 2018 | I70: San Francisco, USA | J70: TRUE | K70: FALSE | L70: FALSE | M70: TRUE | O70: 0 | P70: 1 | Q70: 12 | R70: https://www.coinbase.com/wallet | S70: =IF(M70,N70,"")
A71: 248 | B71: Command R+ | C71: llm | D71: Large Language Models | E71: 4.25 | F71: 4.3 | G71: 4.2 | H71: 2024 | J71: TRUE | K71: FALSE | L71: FALSE | M71: TRUE | O71: 0 | P71: 2 | Q71: 15 | R71: https://cohere.com | S71: =IF(M71,N71,"")
A72: 218 | B72: Consensus | C72: ai-productivity | D72: AI Productivity | E72: 4.55 | F72: 4.6 | G72: 4.5 | H72: 2022 | J72: TRUE | K72: FALSE | L72: TRUE | M72: TRUE | N72: 10 | O72: 10 | P72: 3 | Q72: 6 | R72: https://consensus.app | S72: =IF(M72,N72,"")
A73: 45 | B73: Constant Contact | C73: email-marketing | D73: Email Marketing | E73: 4.15 | F73: 4 | G73: 4.3 | H73: 1995 | I73: Waltham, MA | J73: FALSE | K73: FALSE | L73: FALSE | M73: TRUE | N73: 12 | O73: 80 | P73: 3 | Q73: 15 | R73: https://www.constantcontact.com | S73: =IF(M73,N73,"")
A74: 27 | B74: Copper | C74: crm | D74: CRM | E74: 4.45 | F74: 4.5 | G74: 4.4 | H74: 2013 | I74: San Francisco, CA | J74: FALSE | K74: FALSE | L74: FALSE | M74: TRUE | N74: 12 | O74: 134 | P74: 4 | Q74: 9 | R74: https://www.copper.com | S74: =IF(M74,N74,"")
A75: 155 | B75: Copy.ai | C75: ai-writing | D75: AI Writing | E75: 4.6 | F75: 4.7 | G75: 4.5 | H75: 2020 | J75: FALSE | K75: FALSE | L75: TRUE | M75: TRUE | N75: 1000 | O75: 3000 | P75: 4 | Q75: 10 | R75: https://www.copy.ai | S75: =IF(M75,N75,"")
A76: 195 | B76: Copysmith | C76: ai-writing | D76: AI Writing | E76: 4.35 | F76: 4.4 | G76: 4.3 | H76: 2020 | J76: FALSE | K76: FALSE | L76: TRUE | M76: TRUE | N76: 19 | O76: 49 | P76: 3 | Q76: 11 | R76: https://copysmith.ai | S76: =IF(M76,N76,"")
A77: 150 | B77: CorelDRAW | C77: design-tools | D77: Design Tools | E77: 4.4 | F77: 4.3 | G77: 4.5 | H77: 1989 | I77: Ottawa, Canada | J77: FALSE | K77: FALSE | L77: FALSE | M77: TRUE | N77: 33.5 | O77: 779 | P77: 3 | Q77: 4 | R77: https://www.coreldraw.com | S77: =IF(M77,N77,"")
A78: 269 | B78: Cornix | C78: crypto-trading-bots | D78: Crypto Trading Bots | E78: 4.1 | F78: 4.1 | H78: 2019 | I78: Israel | J78: TRUE | K78: FALSE | L78: FALSE | M78: TRUE | N78: 19 | O78: 59 | P78: 4 | Q78: 6 | R78: https://www.cornix.io | S78: =IF(M78,N78,"")
A79: 251 | B79: CrewAI | C79: ai-agents | D79: AI Agents | E79: 4.15 | F79: 4.2 | G79: 4.1 | H79: 2024 | J79: TRUE | K79: FALSE | L79: FALSE | M79: TRUE | O79: 0 | P79: 2 | Q79: 17 | R79: https://crewai.com | S79: =IF(M79,N79,"")
A80: 266 | B80: Cryptohopper | C80: crypto-trading-bots | D80: Crypto Trading Bots | E80: 4 | F80: 4 | H80: 2017 | I80: Amsterdam, Netherlands | J80: TRUE | K80: FALSE | L80: FALSE | M80: TRUE | N80: 29 | O80: 129 | P80: 4 | Q80: 7 | R80: https://www.cryptohopper.com | S80: =IF(M80,N80,"")
A81: 177 | B81: Cursor | C81: ai-coding | D81: AI Coding | E81: 4.75 | F81: 4.7 | G81: 4.8 | H81: 2023 | J81: TRUE | K81: FALSE | L81: FALSE | M81: TRUE | N81: 20 | O81: 40 | P81: 3 | Q81: 12 | R81: https://cursor.com | S81: =IF(M81,N81,"")
A82: 325 | B82: Curve Finance | C82: dex | D82: DEX | H82: 2020 | I82: Decentralized | J82: TRUE | K82: FALSE | L82: FALSE | M82: FALSE | N82: 0.04 | O82: 0.04 | P82: 4 | Q82: 11 | R82: https://curve.fi | S82: =IF(M82,N82,"")
A83: 166 | B83: CyberGhost | C83: vpn | D83: VPN | E83: 4.4 | F83: 4.3 | G83: 4.5 | H83: 2011 | J83: FALSE | K83: FALSE | L83: FALSE | M83: TRUE | N83: 4.29 | O83: 12.99 | P83: 2 | Q83: 10 | R83: https://www.cyberghostvpn.com | S83: =IF(M83,N83,"")
A84: 168 | B84: DALL-E 3 | C84: ai-image | D84: AI Image Generators | E84: 4.45 | F84: 4.5 | G84: 4.4 | H84: 2023 | J84: FALSE | K84: FALSE | L84: FALSE | M84: TRUE | N84: 20 | O84: 20 | P84: 1 | Q84: 4 | R84: https://openai.com/dall-e-3 | S84: =IF(M84,N84,"")
A85: 133 | B85: Daily | C85: video-conferencing | D85: Video Conferencing | E85: 4.7 | F85: 4.7 | G85: 4.7 | H85: 2016 | I85: San Francisco, CA | J85: TRUE | K85: FALSE | L85: TRUE | M85: TRUE | O85: 0 | P85: 3 | Q85: 12 | R85: https://www.daily.co | S85: =IF(M85,N85,"")
A86: 160 | B86: Dashlane | C86: password-managers | D86: Password Managers | E86: 4.5 | F86: 4.5 | G86: 4.5 | H86: 2012 | J86: TRUE | K86: FALSE | L86: FALSE | M86: TRUE | N86: 4.99 | O86: 8 | P86: 3 | Q86: 10 | R86: https://www.dashlane.com | S86: =IF(M86,N86,"")
A87: 234 | B87: DataRobot | C87: ai-productivity | D87: AI Productivity | E87: 4.3 | F87: 4.3 | G87: 4.3 | H87: 2012 | J87: TRUE | K87: FALSE | L87: TRUE | M87: TRUE | O87: 0 | P87: 2 | Q87: 11 | R87: https://datarobot.com | S87: =IF(M87,N87,"")
A88: 290 | B88: DeBank | C88: crypto-portfolio-trackers | D88: Crypto Portfolio Trackers | E88: 4.6 | F88: 4.6 | H88: 2018 | I88: Unknown | J88: TRUE | K88: FALSE | L88: FALSE | M88: TRUE | N88: 96 | O88: 96 | P88: 2 | Q88: 8 | R88: https://debank.com | S88: =IF(M88,N88,"")
A89: 236 | B89: DeepSeek | C89: llm | D89: Large Language Models | E89: 4.55 | F89: 4.5 | G89: 4.6 | H89: 2023 | J89: TRUE | K89: FALSE | L89: TRUE | M89: TRUE | O89: 0 | P89: 2 | Q89: 6 | R89: https://www.deepseek.com | S89: =IF(M89,N89,"")
A90: 243 | B90: DeepSeek V3 | C90: llm | D90: Large Language Models | E90: 4.35 | F90: 4.4 | G90: 4.3 | H90: 2024 | J90: TRUE | K90: FALSE | L90: FALSE | M90: TRUE | O90: 0 | P90: 2 | Q90: 18 | R90: https://deepseek.com | S90: =IF(M90,N90,"")
A91: 296 | B91: DefiLlama | C91: defi-tools | D91: DeFi Tools | E91: 4.7 | F91: 4.7 | H91: 2020 | I91: Decentralized | J91: TRUE | K91: FALSE | L91: FALSE | M91: TRUE | O91: 0 | P91: 1 | Q91: 5 | R91: https://defillama.com | S91: =IF(M91,N91,"")
A92: 288 | B92: Delta | C92: crypto-portfolio-trackers | D92: Crypto Portfolio Trackers | E92: 4.2 | F92: 4.2 | H92: 2017 | I92: Belgium | J92: TRUE | K92: FALSE | L92: FALSE | M92: TRUE | N92: 8.99 | O92: 8.99 | P92: 2 | Q92: 8 | R92: https://delta.app | S92: =IF(M92,N92,"")
A93: 148 | B93: Demio | C93: video-conferencing | D93: Video Conferencing | E93: 4.55 | F93: 4.4 | G93: 4.7 | H93: 2016 | I93: Scottsdale, AZ | J93: FALSE | K93: FALSE | L93: FALSE | M93: TRUE | N93: 45 | O93: 196 | P93: 3 | Q93: 8 | R93: https://demio.com | S93: =IF(M93,N93,"")
A94: 229 | B94: Descript | C94: ai-video | D94: AI Video | E94: 4.65 | F94: 4.6 | G94: 4.7 | H94: 2017 | J94: TRUE | K94: FALSE | L94: FALSE | M94: TRUE | N94: 19 | O94: 35 | P94: 3 | Q94: 9 | R94: https://descript.com | S94: =IF(M94,N94,"")
A95: 252 | B95: Devin | C95: ai-agents | D95: AI Agents | E95: 3.95 | F95: 4 | G95: 3.9 | H95: 2024 | J95: FALSE | K95: FALSE | L95: TRUE | M95: TRUE | N95: 20 | O95: 80 | P95: 3 | Q95: 13 | R95: https://devin.ai | S95: =IF(M95,N95,"")
A96: 137 | B96: Dialpad | C96: video-conferencing | D96: Video Conferencing | E96: 4.35 | F96: 4.4 | G96: 4.3 | H96: 2012 | I96: San Francisco, CA | J96: FALSE | K96: FALSE | L96: TRUE | M96: TRUE | N96: 27 | O96: 35 | P96: 3 | Q96: 9 | R96: https://www.dialpad.com | S96: =IF(M96,N96,"")
A97: 73 | B97: DigitalOcean | C97: cloud-hosting | D97: Cloud Hosting | E97: 4.6 | F97: 4.5 | G97: 4.7 | H97: 2011 | I97: New York, NY | J97: TRUE | K97: FALSE | L97: FALSE | M97: TRUE | N97: 4 | O97: 8 | P97: 4 | Q97: 18 | R97: https://www.digitalocean.com | S97: =IF(M97,N97,"")
A98: 42 | B98: Drip | C98: email-marketing | D98: Email Marketing | E98: 4.4 | F98: 4.4 | G98: 4.4 | H98: 2013 | I98: Minneapolis, MN | J98: FALSE | K98: FALSE | L98: FALSE | M98: TRUE | N98: 39 | O98: 39 | P98: 1 | Q98: 12 | R98: https://www.drip.com | S98: =IF(M98,N98,"")
A99: 64 | B99: Duda | C99: website-builders | D99: Website Builders | E99: 4.6 | F99: 4.6 | G99: 4.6 | H99: 2010 | I99: Palo Alto, CA | J99: FALSE | K99: FALSE | L99: FALSE | M99: TRUE | N99: 25 | O99: 199 | P99: 4 | Q99: 15 | R99: https://www.duda.co | S99: =IF(M99,N99,"")
A100: 278 | B100: Dune Analytics | C100: crypto-analytics | D100: Crypto Analytics | E100: 4.6 | F100: 4.6 | H100: 2018 | I100: Oslo, Norway | J100: TRUE | K100: FALSE | L100: TRUE | M100: TRUE | N100: 349 | O100: 399 | P100: 4 | Q100: 8 | R100: https://dune.com | S100: =IF(M100,N100,"")
...

Sheet Pricing Plans
A1: id | B1: product_name | C1: plan_name | D1: price_monthly | E1: price_annual | F1: billing_model
A2: 1 | B2: Notion | C2: Free | D2: 0 | F2: per-seat
A3: 2 | B3: Notion | C3: Plus | D3: 12 | F3: per-seat
A4: 3 | B4: Notion | C4: Business | D4: 18 | F4: per-seat
A5: 4 | B5: Notion | C5: Enterprise | F5: per-seat
A6: 5 | B6: ClickUp | C6: Free | D6: 0 | F6: flat
A7: 6 | B7: ClickUp | C7: Unlimited | D7: 7 | F7: per-seat
A8: 7 | B8: ClickUp | C8: Business | D8: 12 | F8: per-seat
A9: 8 | B9: ClickUp | C9: Enterprise | F9: per-seat
A10: 9 | B10: Asana | C10: Personal | D10: 0 | F10: flat
A11: 10 | B11: Asana | C11: Starter | D11: 10.99 | F11: per-seat
A12: 11 | B12: Asana | C12: Advanced | D12: 24.99 | F12: per-seat
A13: 12 | B13: Asana | C13: Enterprise | F13: per-seat
A14: 13 | B14: monday.com | C14: Free | D14: 0 | F14: flat
A15: 14 | B15: monday.com | C15: Basic | D15: 9 | F15: per-seat
A16: 15 | B16: monday.com | C16: Standard | D16: 12 | F16: per-seat
A17: 16 | B17: monday.com | C17: Pro | D17: 19 | F17: per-seat
A18: 17 | B18: monday.com | C18: Enterprise | F18: per-seat
A19: 18 | B19: Trello | C19: Free | D19: 0 | F19: flat
A20: 19 | B20: Trello | C20: Standard | D20: 5 | F20: per-seat
A21: 20 | B21: Trello | C21: Premium | D21: 10 | F21: per-seat
A22: 21 | B22: Trello | C22: Enterprise | D22: 17.5 | F22: per-seat
A23: 22 | B23: Jira | C23: Free | D23: 0 | F23: flat
A24: 23 | B24: Jira | C24: Standard | D24: 7.91 | F24: per-seat
A25: 24 | B25: Jira | C25: Premium | D25: 14.54 | F25: per-seat
A26: 25 | B26: Jira | C26: Enterprise | F26: per-seat
A27: 26 | B27: Basecamp | C27: Free | D27: 0 | F27: flat
A28: 27 | B28: Basecamp | C28: Basecamp Plus | D28: 15 | F28: per-seat
A29: 28 | B29: Basecamp | C29: Basecamp Pro Unlimited | D29: 299 | F29: flat
A30: 29 | B30: Wrike | C30: Free | D30: 0 | F30: flat
A31: 30 | B31: Wrike | C31: Team | D31: 10 | F31: per-seat
A32: 31 | B32: Wrike | C32: Business | D32: 25 | F32: per-seat
A33: 32 | B33: Wrike | C33: Pinnacle | F33: per-seat
A34: 33 | B34: Teamwork | C34: Free | D34: 0 | F34: flat
A35: 34 | B35: Teamwork | C35: Deliver | D35: 13.99 | F35: per-seat
A36: 35 | B36: Teamwork | C36: Grow | D36: 25.99 | F36: per-seat
A37: 36 | B37: Teamwork | C37: Scale | D37: 69.99 | F37: per-seat
A38: 37 | B38: Linear | C38: Free | D38: 0 | F38: flat
A39: 38 | B39: Linear | C39: Basic | D39: 10 | F39: per-seat
A40: 39 | B40: Linear | C40: Business | D40: 16 | F40: per-seat
A41: 40 | B41: Linear | C41: Enterprise | F41: per-seat
A42: 41 | B42: Height | C42: Free | D42: 0 | F42: flat
A43: 42 | B43: Height | C43: Team | D43: 8.5 | F43: per-seat
A44: 43 | B44: Height | C44: Business | D44: 15 | F44: per-seat
A45: 44 | B45: Hive | C45: Free | D45: 0 | F45: flat
A46: 45 | B46: Hive | C46: Starter | D46: 5 | F46: per-seat
A47: 46 | B47: Hive | C47: Teams | D47: 12 | F47: per-seat
A48: 47 | B48: Hive | C48: Enterprise | F48: per-seat
A49: 48 | B49: Smartsheet | C49: Pro | D49: 9 | F49: per-seat
A50: 49 | B50: Smartsheet | C50: Business | D50: 19 | F50: per-seat
A51: 50 | B51: Smartsheet | C51: Enterprise | F51: per-seat
A52: 51 | B52: Airtable | C52: Free | D52: 0 | F52: flat
A53: 52 | B53: Airtable | C53: Team | D53: 20 | F53: per-seat
A54: 53 | B54: Airtable | C54: Business | D54: 45 | F54: per-seat
A55: 54 | B55: Airtable | C55: Enterprise Scale | F55: per-seat
A56: 55 | B56: Todoist | C56: Beginner | D56: 0 | F56: flat
A57: 56 | B57: Todoist | C57: Pro | D57: 5 | F57: per-seat
A58: 57 | B58: Todoist | C58: Business | D58: 8 | F58: per-seat
A59: 58 | B59: Miro | C59: Free | D59: 0 | F59: flat
A60: 59 | B60: Miro | C60: Starter | D60: 8 | F60: per-seat
A61: 60 | B61: Miro | C61: Business | D61: 20 | F61: per-seat
A62: 61 | B62: Miro | C62: Enterprise | F62: per-seat
A63: 62 | B63: Coda | C63: Free | D63: 0 | F63: flat
A64: 63 | B64: Coda | C64: Pro | D64: 10 | F64: flat
A65: 64 | B65: Coda | C65: Team | D65: 30 | F65: flat
A66: 65 | B66: Coda | C66: Enterprise | F66: flat
A67: 66 | B67: Shortcut (formerly Clubhouse) | C67: Free | D67: 0 | F67: flat
A68: 67 | B68: Shortcut (formerly Clubhouse) | C68: Team | D68: 8.5 | F68: per-seat
A69: 68 | B69: Shortcut (formerly Clubhouse) | C69: Business | D69: 12 | F69: per-seat
A70: 69 | B70: Shortcut (formerly Clubhouse) | C70: Enterprise | F70: per-seat
A71: 70 | B71: Nifty | C71: Free | D71: 0 | F71: flat
A72: 71 | B72: Nifty | C72: Starter | D72: 39 | E72: 468 | F72: flat
A73: 72 | B73: Nifty | C73: Business | D73: 124 | E73: 1488 | F73: flat
A74: 73 | B74: Nifty | C74: Unlimited | D74: 399 | E74: 4788 | F74: flat
A75: 74 | B75: Zoho Projects | C75: Free | D75: 0 | F75: flat
A76: 75 | B76: Zoho Projects | C76: Premium | D76: 5 | F76: per-seat
A77: 76 | B77: Zoho Projects | C77: Enterprise | D77: 10 | F77: per-seat
A78: 77 | B78: Salesforce | C78: Starter Suite | D78: 25 | F78: per-seat
A79: 78 | B79: Salesforce | C79: Pro Suite | D79: 100 | F79: per-seat
A80: 79 | B80: Salesforce | C80: Enterprise | D80: 165 | F80: per-seat
A81: 80 | B81: Salesforce | C81: Unlimited | D81: 330 | F81: per-seat
A82: 81 | B82: HubSpot | C82: Free Tools | D82: 0 | F82: flat
A83: 82 | B83: HubSpot | C83: Starter | D83: 20 | F83: per-seat
A84: 83 | B84: HubSpot | C84: Professional | D84: 890 | F84: flat
A85: 84 | B85: HubSpot | C85: Enterprise | D85: 3600 | F85: flat
A86: 85 | B86: Pipedrive | C86: Essential | D86: 14 | E86: 168 | F86: per-seat
A87: 86 | B87: Pipedrive | C87: Growth | D87: 39 | E87: 468 | F87: per-seat
A88: 87 | B88: Pipedrive | C88: Professional | D88: 49 | E88: 588 | F88: per-seat
A89: 88 | B89: Pipedrive | C89: Power | D89: 64 | E89: 768 | F89: per-seat
A90: 89 | B90: Pipedrive | C90: Enterprise | D90: 99 | E90: 1188 | F90: per-seat
A91: 90 | B91: Zoho CRM | C91: Free | D91: 0 | F91: flat
A92: 91 | B92: Zoho CRM | C92: Standard | D92: 20 | F92: per-seat
A93: 92 | B93: Zoho CRM | C93: Professional | D93: 35 | F93: per-seat
A94: 93 | B94: Zoho CRM | C94: Enterprise | D94: 50 | F94: per-seat
A95: 94 | B95: Zoho CRM | C95: Ultimate | D95: 65 | F95: per-seat
A96: 95 | B96: Freshsales | C96: Free | D96: 0 | F96: flat
A97: 96 | B97: Freshsales | C97: Growth | D97: 11 | F97: per-seat
A98: 97 | B98: Freshsales | C98: Pro | D98: 47 | F98: per-seat
A99: 98 | B99: Freshsales | C99: Enterprise | D99: 71 | F99: per-seat
A100: 99 | B100: Close | C100: Startup | D100: 49 | F100: per-seat
...

Sheet Category Summary
A1: category_name | B1: product_count | C1: avg_rating | D1: avg_entry_price | E1: free_tier_count | F1: free_tier_pct | G1: avg_feature_count
A2: AI Agents | B2: =COUNTIF(Products!D2:D332,A2) | C2: =ROUND(AVERAGEIF(Products!D2:D332,A2,Products!E2:E332),2) | D2: =IFERROR(ROUND(AVERAGEIF(Products!D2:D332,A2,Products!S2:S332),2),"N/A") | E2: =COUNTIFS(Products!D2:D332,A2,Products!J2:J332,TRUE) | F2: =ROUND(E2/B2*100,1) | G2: =ROUND(AVERAGEIF(Products!D2:D332,A2,Products!Q2:Q332),2)
A3: AI Assistants | B3: =COUNTIF(Products!D2:D332,A3) | C3: =ROUND(AVERAGEIF(Products!D2:D332,A3,Products!E2:E332),2) | D3: =IFERROR(ROUND(AVERAGEIF(Products!D2:D332,A3,Products!S2:S332),2),"N/A") | E3: =COUNTIFS(Products!D2:D332,A3,Products!J2:J332,TRUE) | F3: =ROUND(E3/B3*100,1) | G3: =ROUND(AVERAGEIF(Products!D2:D332,A3,Products!Q2:Q332),2)
A4: AI Coding | B4: =COUNTIF(Products!D2:D332,A4) | C4: =ROUND(AVERAGEIF(Products!D2:D332,A4,Products!E2:E332),2) | D4: =IFERROR(ROUND(AVERAGEIF(Products!D2:D332,A4,Products!S2:S332),2),"N/A") | E4: =COUNTIFS(Products!D2:D332,A4,Products!J2:J332,TRUE) | F4: =ROUND(E4/B4*100,1) | G4: =ROUND(AVERAGEIF(Products!D2:D332,A4,Products!Q2:Q332),2)
A5: AI Image Generators | B5: =COUNTIF(Products!D2:D332,A5) | C5: =ROUND(AVERAGEIF(Products!D2:D332,A5,Products!E2:E332),2) | D5: =IFERROR(ROUND(AVERAGEIF(Products!D2:D332,A5,Products!S2:S332),2),"N/A") | E5: =COUNTIFS(Products!D2:D332,A5,Products!J2:J332,TRUE) | F5: =ROUND(E5/B5*100,1) | G5: =ROUND(AVERAGEIF(Products!D2:D332,A5,Products!Q2:Q332),2)
A6: AI Productivity | B6: =COUNTIF(Products!D2:D332,A6) | C6: =ROUND(AVERAGEIF(Products!D2:D332,A6,Products!E2:E332),2) | D6: =IFERROR(ROUND(AVERAGEIF(Products!D2:D332,A6,Products!S2:S332),2),"N/A") | E6: =COUNTIFS(Products!D2:D332,A6,Products!J2:J332,TRUE) | F6: =ROUND(E6/B6*100,1) | G6: =ROUND(AVERAGEIF(Products!D2:D332,A6,Products!Q2:Q332),2)
A7: AI Video | B7: =COUNTIF(Products!D2:D332,A7) | C7: =ROUND(AVERAGEIF(Products!D2:D332,A7,Products!E2:E332),2) | D7: =IFERROR(ROUND(AVERAGEIF(Products!D2:D332,A7,Products!S2:S332),2),"N/A") | E7: =COUNTIFS(Products!D2:D332,A7,Products!J2:J332,TRUE) | F7: =ROUND(E7/B7*100,1) | G7: =ROUND(AVERAGEIF(Products!D2:D332,A7,Products!Q2:Q332),2)
A8: AI Voice & Audio | B8: =COUNTIF(Products!D2:D332,A8) | C8: =ROUND(AVERAGEIF(Products!D2:D332,A8,Products!E2:E332),2) | D8: =IFERROR(ROUND(AVERAGEIF(Products!D2:D332,A8,Products!S2:S332),2),"N/A") | E8: =COUNTIFS(Products!D2:D332,A8,Products!J2:J332,TRUE) | F8: =ROUND(E8/B8*100,1) | G8: =ROUND(AVERAGEIF(Products!D2:D332,A8,Products!Q2:Q332),2)
A9: AI Writing | B9: =COUNTIF(Products!D2:D332,A9) | C9: =ROUND(AVERAGEIF(Products!D2:D332,A9,Products!E2:E332),2) | D9: =IFERROR(ROUND(AVERAGEIF(Products!D2:D332,A9,Products!S2:S332),2),"N/A") | E9: =COUNTIFS(Products!D2:D332,A9,Products!J2:J332,TRUE) | F9: =ROUND(E9/B9*100,1) | G9: =ROUND(AVERAGEIF(Products!D2:D332,A9,Products!Q2:Q332),2)
A10: Accounting | B10: =COUNTIF(Products!D2:D332,A10) | C10: =ROUND(AVERAGEIF(Products!D2:D332,A10,Products!E2:E332),2) | D10: =IFERROR(ROUND(AVERAGEIF(Products!D2:D332,A10,Products!S2:S332),2),"N/A") | E10: =COUNTIFS(Products!D2:D332,A10,Products!J2:J332,TRUE) | F10: =ROUND(E10/B10*100,1) | G10: =ROUND(AVERAGEIF(Products!D2:D332,A10,Products!Q2:Q332),2)
A11: CRM | B11: =COUNTIF(Products!D2:D332,A11) | C11: =ROUND(AVERAGEIF(Products!D2:D332,A11,Products!E2:E332),2) | D11: =IFERROR(ROUND(AVERAGEIF(Products!D2:D332,A11,Products!S2:S332),2),"N/A") | E11: =COUNTIFS(Products!D2:D332,A11,Products!J2:J332,TRUE) | F11: =ROUND(E11/B11*100,1) | G11: =ROUND(AVERAGEIF(Products!D2:D332,A11,Products!Q2:Q332),2)
A12: Cloud Hosting | B12: =COUNTIF(Products!D2:D332,A12) | C12: =ROUND(AVERAGEIF(Products!D2:D332,A12,Products!E2:E332),2) | D12: =IFERROR(ROUND(AVERAGEIF(Products!D2:D332,A12,Products!S2:S332),2),"N/A") | E12: =COUNTIFS(Products!D2:D332,A12,Products!J2:J332,TRUE) | F12: =ROUND(E12/B12*100,1) | G12: =ROUND(AVERAGEIF(Products!D2:D332,A12,Products!Q2:Q332),2)
A13: Crypto Analytics | B13: =COUNTIF(Products!D2:D332,A13) | C13: =ROUND(AVERAGEIF(Products!D2:D332,A13,Products!E2:E332),2) | D13: =IFERROR(ROUND(AVERAGEIF(Products!D2:D332,A13,Products!S2:S332),2),"N/A") | E13: =COUNTIFS(Products!D2:D332,A13,Products!J2:J332,TRUE) | F13: =ROUND(E13/B13*100,1) | G13: =ROUND(AVERAGEIF(Products!D2:D332,A13,Products!Q2:Q332),2)
A14: Crypto Exchanges | B14: =COUNTIF(Products!D2:D332,A14) | C14: =ROUND(AVERAGEIF(Products!D2:D332,A14,Products!E2:E332),2) | D14: =IFERROR(ROUND(AVERAGEIF(Products!D2:D332,A14,Products!S2:S332),2),"N/A") | E14: =COUNTIFS(Products!D2:D332,A14,Products!J2:J332,TRUE) | F14: =ROUND(E14/B14*100,1) | G14: =ROUND(AVERAGEIF(Products!D2:D332,A14,Products!Q2:Q332),2)
A15: Crypto Portfolio Trackers | B15: =COUNTIF(Products!D2:D332,A15) | C15: =ROUND(AVERAGEIF(Products!D2:D332,A15,Products!E2:E332),2) | D15: =IFERROR(ROUND(AVERAGEIF(Products!D2:D332,A15,Products!S2:S332),2),"N/A") | E15: =COUNTIFS(Products!D2:D332,A15,Products!J2:J332,TRUE) | F15: =ROUND(E15/B15*100,1) | G15: =ROUND(AVERAGEIF(Products!D2:D332,A15,Products!Q2:Q332),2)
A16: Crypto Tax | B16: =COUNTIF(Products!D2:D332,A16) | C16: =ROUND(AVERAGEIF(Products!D2:D332,A16,Products!E2:E332),2) | D16: =IFERROR(ROUND(AVERAGEIF(Products!D2:D332,A16,Products!S2:S332),2),"N/A") | E16: =COUNTIFS(Products!D2:D332,A16,Products!J2:J332,TRUE) | F16: =ROUND(E16/B16*100,1) | G16: =ROUND(AVERAGEIF(Products!D2:D332,A16,Products!Q2:Q332),2)
A17: Crypto Telegram Bots | B17: =COUNTIF(Products!D2:D332,A17) | C17: =ROUND(AVERAGEIF(Products!D2:D332,A17,Products!E2:E332),2) | D17: =IFERROR(ROUND(AVERAGEIF(Products!D2:D332,A17,Products!S2:S332),2),"N/A") | E17: =COUNTIFS(Products!D2:D332,A17,Products!J2:J332,TRUE) | F17: =ROUND(E17/B17*100,1) | G17: =ROUND(AVERAGEIF(Products!D2:D332,A17,Products!Q2:Q332),2)
A18: Crypto Trading Bots | B18: =COUNTIF(Products!D2:D332,A18) | C18: =ROUND(AVERAGEIF(Products!D2:D332,A18,Products!E2:E332),2) | D18: =IFERROR(ROUND(AVERAGEIF(Products!D2:D332,A18,Products!S2:S332),2),"N/A") | E18: =COUNTIFS(Products!D2:D332,A18,Products!J2:J332,TRUE) | F18: =ROUND(E18/B18*100,1) | G18: =ROUND(AVERAGEIF(Products!D2:D332,A18,Products!Q2:Q332),2)
A19: Crypto Wallets | B19: =COUNTIF(Products!D2:D332,A19) | C19: =ROUND(AVERAGEIF(Products!D2:D332,A19,Products!E2:E332),2) | D19: =IFERROR(ROUND(AVERAGEIF(Products!D2:D332,A19,Products!S2:S332),2),"N/A") | E19: =COUNTIFS(Products!D2:D332,A19,Products!J2:J332,TRUE) | F19: =ROUND(E19/B19*100,1) | G19: =ROUND(AVERAGEIF(Products!D2:D332,A19,Products!Q2:Q332),2)
A20: DEX | B20: =COUNTIF(Products!D2:D332,A20) | C20: =ROUND(AVERAGEIF(Products!D2:D332,A20,Products!E2:E332),2) | D20: =IFERROR(ROUND(AVERAGEIF(Products!D2:D332,A20,Products!S2:S332),2),"N/A") | E20: =COUNTIFS(Products!D2:D332,A20,Products!J2:J332,TRUE) | F20: =ROUND(E20/B20*100,1) | G20: =ROUND(AVERAGEIF(Products!D2:D332,A20,Products!Q2:Q332),2)
A21: DeFi Tools | B21: =COUNTIF(Products!D2:D332,A21) | C21: =ROUND(AVERAGEIF(Products!D2:D332,A21,Products!E2:E332),2) | D21: =IFERROR(ROUND(AVERAGEIF(Products!D2:D332,A21,Products!S2:S332),2),"N/A") | E21: =COUNTIFS(Products!D2:D332,A21,Products!J2:J332,TRUE) | F21: =ROUND(E21/B21*100,1) | G21: =ROUND(AVERAGEIF(Products!D2:D332,A21,Products!Q2:Q332),2)
A22: Design Tools | B22: =COUNTIF(Products!D2:D332,A22) | C22: =ROUND(AVERAGEIF(Products!D2:D332,A22,Products!E2:E332),2) | D22: =IFERROR(ROUND(AVERAGEIF(Products!D2:D332,A22,Products!S2:S332),2),"N/A") | E22: =COUNTIFS(Products!D2:D332,A22,Products!J2:J332,TRUE) | F22: =ROUND(E22/B22*100,1) | G22: =ROUND(AVERAGEIF(Products!D2:D332,A22,Products!Q2:Q332),2)
A23: Email Marketing | B23: =COUNTIF(Products!D2:D332,A23) | C23: =ROUND(AVERAGEIF(Products!D2:D332,A23,Products!E2:E332),2) | D23: =IFERROR(ROUND(AVERAGEIF(Products!D2:D332,A23,Products!S2:S332),2),"N/A") | E23: =COUNTIFS(Products!D2:D332,A23,Products!J2:J332,TRUE) | F23: =ROUND(E23/B23*100,1) | G23: =ROUND(AVERAGEIF(Products!D2:D332,A23,Products!Q2:Q332),2)
A24: Large Language Models | B24: =COUNTIF(Products!D2:D332,A24) | C24: =ROUND(AVERAGEIF(Products!D2:D332,A24,Products!E2:E332),2) | D24: =IFERROR(ROUND(AVERAGEIF(Products!D2:D332,A24,Products!S2:S332),2),"N/A") | E24: =COUNTIFS(Products!D2:D332,A24,Products!J2:J332,TRUE) | F24: =ROUND(E24/B24*100,1) | G24: =ROUND(AVERAGEIF(Products!D2:D332,A24,Products!Q2:Q332),2)
A25: Password Managers | B25: =COUNTIF(Products!D2:D332,A25) | C25: =ROUND(AVERAGEIF(Products!D2:D332,A25,Products!E2:E332),2) | D25: =IFERROR(ROUND(AVERAGEIF(Products!D2:D332,A25,Products!S2:S332),2),"N/A") | E25: =COUNTIFS(Products!D2:D332,A25,Products!J2:J332,TRUE) | F25: =ROUND(E25/B25*100,1) | G25: =ROUND(AVERAGEIF(Products!D2:D332,A25,Products!Q2:Q332),2)
A26: Project Management | B26: =COUNTIF(Products!D2:D332,A26) | C26: =ROUND(AVERAGEIF(Products!D2:D332,A26,Products!E2:E332),2) | D26: =IFERROR(ROUND(AVERAGEIF(Products!D2:D332,A26,Products!S2:S332),2),"N/A") | E26: =COUNTIFS(Products!D2:D332,A26,Products!J2:J332,TRUE) | F26: =ROUND(E26/B26*100,1) | G26: =ROUND(AVERAGEIF(Products!D2:D332,A26,Products!Q2:Q332),2)
A27: VPN | B27: =COUNTIF(Products!D2:D332,A27) | C27: =ROUND(AVERAGEIF(Products!D2:D332,A27,Products!E2:E332),2) | D27: =IFERROR(ROUND(AVERAGEIF(Products!D2:D332,A27,Products!S2:S332),2),"N/A") | E27: =COUNTIFS(Products!D2:D332,A27,Products!J2:J332,TRUE) | F27: =ROUND(E27/B27*100,1) | G27: =ROUND(AVERAGEIF(Products!D2:D332,A27,Products!Q2:Q332),2)
A28: Video Conferencing | B28: =COUNTIF(Products!D2:D332,A28) | C28: =ROUND(AVERAGEIF(Products!D2:D332,A28,Products!E2:E332),2) | D28: =IFERROR(ROUND(AVERAGEIF(Products!D2:D332,A28,Products!S2:S332),2),"N/A") | E28: =COUNTIFS(Products!D2:D332,A28,Products!J2:J332,TRUE) | F28: =ROUND(E28/B28*100,1) | G28: =ROUND(AVERAGEIF(Products!D2:D332,A28,Products!Q2:Q332),2)
A29: Website Builders | B29: =COUNTIF(Products!D2:D332,A29) | C29: =ROUND(AVERAGEIF(Products!D2:D332,A29,Products!E2:E332),2) | D29: =IFERROR(ROUND(AVERAGEIF(Products!D2:D332,A29,Products!S2:S332),2),"N/A") | E29: =COUNTIFS(Products!D2:D332,A29,Products!J2:J332,TRUE) | F29: =ROUND(E29/B29*100,1) | G29: =ROUND(AVERAGEIF(Products!D2:D332,A29,Products!Q2:Q332),2)
A31: Note: 'DEX' avg_entry_price shows N/A — its listed prices are swap-fee %, not USD/month subscriptions.

Sheet Billing Models
A1: billing_model | B1: plan_count | C1: pct_of_plans
A2: flat | B2: =COUNTIF('Pricing Plans'!F2:F1014,A2) | C2: =ROUND(B2/SUM($B$2:$B$5)*100,1)
A3: per-seat | B3: =COUNTIF('Pricing Plans'!F2:F1014,A3) | C3: =ROUND(B3/SUM($B$2:$B$5)*100,1)
A4: usage-based | B4: =COUNTIF('Pricing Plans'!F2:F1014,A4) | C4: =ROUND(B4/SUM($B$2:$B$5)*100,1)
A5: per-project | B5: =COUNTIF('Pricing Plans'!F2:F1014,A5) | C5: =ROUND(B5/SUM($B$2:$B$5)*100,1)
